fastdotcom/__init__.py
fastdotcom-0.0.5.dist-info/licenses/LICENSE
fastdotcom-0.0.5.dist-info/METADATA
fastdotcom-0.0.5.dist-info/WHEEL
fastdotcom-0.0.5.dist-info/top_level.txt
fastdotcom-0.0.5.dist-info/zip-safe
fastdotcom-0.0.5.dist-info/RECORD
